Workbook

Sheet Company_Info
B3: Company Name | C3: Emaar Properties PJSC
B4: Headquarters | C4: Dubai,UAE
B5: Industry | C5: Real Estate
B6: Analysis period | C6: FY2023-FY2025
B7: Currency | C7: AED
B8: Project Type | C8: Independent Portfolio Project
B9: Data Source | C9: Emaar Properties PJSC Annual Reports
B10: Prepared By | C10: Anas Abdul Rahim Khatib
B13: Year | C13: Reports
B14: 2023 | C14: Emaar Properties PJSC Annual Report 2023
B15: 2024 | C15: Emaar Properties PJSC Annual Report 2024
B16: 2025 | C16: Emaar Properties PJSC Annual Report 2025

Sheet Dashboard
A1: Emaar Properties PJSC- Financial Analysis & 3-Year Financial Model
A3: Revenue | D3: Net Profit | G3: Net Profit Margin | J3: Profit Before Tax | M3: Gross Profit
A4: FY2025A | B4: FY2028F | D4: FY2025A | E4: FY2028F | G4: FY2025A | H4: FY2028F | J4: FY2025A | K4: FY2028F | M4: FY2025A | N4: FY2028F
A5: =Forecast!J15 -> 49557.263 | B5: =Forecast!M15 -> 125072.04 | D5: =Forecast!J18 -> 22325.535 | E5: =Forecast!M18 -> 75167.988 | G5: =D5/A5 -> 0.45049976 | H5: =E5/B5 -> 0.60099752 | J5: =Forecast!J17 -> 25656.434 | K5: =Forecast!M17 -> 93284.854 | M5: =Forecast!J16 -> 27227.303 | N5: =Forecast!M16 -> 108333.7

Sheet Historical_IS
B2: Consolidated income statement of 2023,2024&2025
B3: Particulars | C3: Amount(AED in Milllions) 2023 | D3: Amount(AED in Milllions) 2024 | E3: Amount(AED in Milllions) 2025
B4: Revenue | C4: 26749.821 | D4: 35504.92 | E4: 49557.263
B5: Gross profit | C5: 16865.324 | D5: 20380.554 | E5: 27227.303
B6: Profit before tax | C6: 15061.564 | D6: 18899.78 | E6: 25656.434
B7: Income tax credit / (expense) | C7: -232.414 | D7: -1450.707 | E7: -3330.899
B8: Net Profit Attributable to Owners of the Parent | C8: 11629.238 | D8: 13513.938 | E8: 17599.179
B11: Profit for the year
B12: Total | C12: 14829.15 | D12: 17449.073 | E12: 22325.535
B13: Attributable to: Owners of the parent | C13: 11629.238 | D13: 13513.938 | E13: 17599.179
B14: Attributable to: Non-controlling interests | C14: 3199.912 | D14: 3935.135 | E14: 4726.356

Sheet Historical_BS
B2: Consolidated statement of financial position | C2: Amount(AED in Milllions) 2023 | D2: Amount(AED in Milllions) 2024 | E2: Amount(AED in Milllions) 2025
B3: Total assets | C3: 139397.23 | D3: 160222.37 | E3: 186700.69
B4: Total liabilities | C4: 52566.214 | D4: 64152.334 | E4: 79024.38
B5: Equity attributable to owners of the parent | C5: 77724.133 | D5: 85428.227 | E5: 94278.017
B6: Non-controlling interests | C6: 9106.885 | D6: 10641.807 | E6: 13398.29
B7: Total equity | C7: 86831.018 | D7: 96070.034 | E7: 107676.31

Sheet Historical_CF
B3: Consolidated statement of cash flows | C3: Amount(AED in Milllions) 2023 | D3: Amount(AED in Milllions) 2024 | E3: Amount(AED in Milllions) 2025
B4: Net cash flows from operating activities | C4: 19831.247 | D4: 24481.462 | E4: 33458.369
B5: Net cash flows (used in)/ from investing activities | C5: -5309.174 | D5: -2270.22 | E5: -6960.62
B6: Net cash flows (used in)/ from financing activities | C6: -6185.538 | D6: -8759.759 | E6: -12615.401
B7: Increase in cash and cash equivalents | C7: 8336.532 | D7: 13451.483 | E7: 13882.348
B8: Cash and cash equivalents at the end of the year | C8: 25624.573 | D8: 38631.997 | E8: 52632.912

Sheet Ratio_Analysis
A2: Ratio Analysis | B2: FY2023 | C2: FY2024 | D2: FY2025
A3: Profitabillity Ratios
A4: Net Profit Margin | B4: =Historical_IS!C12/Historical_IS!C4 -> 0.55436446 | C4: =Historical_IS!D12/Historical_IS!D4 -> 0.49145507 | D4: =Historical_IS!E12/Historical_IS!E4 -> 0.45049976
A5: Return on Assets (ROA) | B5: =Historical_IS!C12/Historical_BS!C3 -> 0.10638052 | C5: =Historical_IS!D12/Historical_BS!D3 -> 0.10890535 | D5: =Historical_IS!E12/Historical_BS!E3 -> 0.11957929
A6: Return on Equity (ROE) | B6: =Historical_IS!C12/Historical_BS!C7 -> 0.17078171 | C6: =Historical_IS!D12/Historical_BS!D7 -> 0.18162868 | D6: =Historical_IS!E12/Historical_BS!E7 -> 0.20733935
A7: Liquidity Ratio
A8: Current Ratio | B8: Not Disclosed | C8: Not Disclosed | D8: Not Disclosed
A9: Leverage Ratio | B9: =Historical_BS!C4/Historical_BS!C7 -> 0.60538521 | C9: =Historical_BS!D4/Historical_BS!D7 -> 0.66776633 | D9: =Historical_BS!E4/Historical_BS!E7 -> 0.73390686
A10: Debt To Equity Ratio | B10: Not Disclosed | C10: Not Disclosed | D10: Not Disclosed
A11: Efficiency Ratio
A12: Asset Turnover | B12: =Historical_IS!C4/Historical_BS!C3 -> 0.19189636 | C12: =Historical_IS!D4/Historical_BS!D3 -> 0.22159777 | D12: =Historical_IS!E4/Historical_BS!E3 -> 0.26543696

Sheet Common_Size
B3: Section-1 Common Size Statement
B5: Common Size Income Statement | C5: FY2023 | D5: FY2024 | E5: FY2025
B6: Revenue | C6: =Historical_IS!C4/Historical_IS!C4 -> 1 | D6: =Historical_IS!D4/Historical_IS!D4 -> 1 | E6: =Historical_IS!E4/Historical_IS!E4 -> 1
B7: Gross Profit | C7: =Historical_IS!C5/Historical_IS!C4 -> 0.63048362 | D7: =Historical_IS!D5/Historical_IS!D4 -> 0.57402056 | E7: =Historical_IS!E5/Historical_IS!E4 -> 0.54941095
B8: Profit Before Tax | C8: =Historical_IS!C6/Historical_IS!C4 -> 0.56305289 | D8: =Historical_IS!D6/Historical_IS!D4 -> 0.53231439 | E8: =Historical_IS!E6/Historical_IS!E4 -> 0.51771289
B9: Income Tax Credit/(Expense) | C9: =Historical_IS!C7/Historical_IS!C4 -> -0.008688432 | D9: =Historical_IS!D7/Historical_IS!D4 -> -0.040859323 | E9: =Historical_IS!E7/Historical_IS!E4 -> -0.067213135
B10: Profit for the Year | C10: =Historical_IS!C12/Historical_IS!C4 -> 0.55436446 | D10: =Historical_IS!D12/Historical_IS!D4 -> 0.49145507 | E10: =Historical_IS!E12/Historical_IS!E4 -> 0.45049976
B14: Section-2 Common Size Statement of Financial Statement
B16: Common Size Statement of Financial Statement | C16: FY2023 | D16: FY2024 | E16: FY2025
B17: Total Assets | C17: =Historical_BS!C3/Historical_BS!C3 -> 1 | D17: =Historical_BS!D3/Historical_BS!D3 -> 1 | E17: =Historical_BS!E3/Historical_BS!E3 -> 1
B18: Total Liablities | C18: =Historical_BS!C4/Historical_BS!C3 -> 0.37709654 | D18: =Historical_BS!D4/Historical_BS!D3 -> 0.40039562 | E18: =Historical_BS!E4/Historical_BS!E3 -> 0.42326775
B19: Equity Attributable to Owners of the Parent | C19: =Historical_BS!C5/Historical_BS!C3 -> 0.557573 | D19: =Historical_BS!D5/Historical_BS!D3 -> 0.5331854 | E19: =Historical_BS!E5/Historical_BS!E3 -> 0.50496877
B20: Non-Controlling Interest | C20: =Historical_BS!C6/Historical_BS!C3 -> 0.065330458 | D20: =Historical_BS!D6/Historical_BS!D3 -> 0.066418985 | E20: =Historical_BS!E6/Historical_BS!E3 -> 0.071763475
B21: Total Equity | C21: =Historical_BS!C7/Historical_BS!C3 -> 0.62290346 | D21: =Historical_BS!D7/Historical_BS!D3 -> 0.59960438 | E21: =Historical_BS!E7/Historical_BS!E3 -> 0.57673225

Sheet Forecast
B3: Financial Trend | C3: Amount(AED in Milllions) 2023 | D3: Amount(AED in Milllions) 2024 | E3: Amount(AED in Milllions) 2025
B4: Revenue | C4: =Historical_IS!C4 -> 26749.821 | D4: =Historical_IS!D4 -> 35504.92 | E4: =Historical_IS!E4 -> 49557.263
B5: Gross Profit | C5: =Historical_IS!C5 -> 16865.324 | D5: =Historical_IS!D5 -> 20380.554 | E5: =Historical_IS!E5 -> 27227.303
B6: Profit Before Tax | C6: =Historical_IS!C6 -> 15061.564 | D6: =Historical_IS!D6 -> 18899.78 | E6: =Historical_IS!E6 -> 25656.434
B7: Profit for the Year | C7: =Historical_IS!C12 -> 14829.15 | D7: =Historical_IS!D12 -> 17449.073 | E7: =Historical_IS!E12 -> 22325.535
B8: Total Assets | C8: =Historical_BS!C3 -> 139397.23 | D8: =Historical_BS!D3 -> 160222.37 | E8: =Historical_BS!E3 -> 186700.69
B9: Total Liabilities | C9: =Historical_BS!C4 -> 52566.214 | D9: =Historical_BS!D4 -> 64152.334 | E9: =Historical_BS!E4 -> 79024.38
B10: Total Equity | C10: =Historical_BS!C7 -> 86831.018 | D10: =Historical_BS!D7 -> 96070.034 | E10: =Historical_BS!E7 -> 107676.31
B11: Operating Cash Flow | C11: =Historical_CF!C4 -> 19831.247 | D11: =Historical_CF!D4 -> 24481.462 | E11: =Historical_CF!E4 -> 33458.369
B14: Growth Analysis | C14: FY2023 | D14: FY2024 | E14: FY2025 | G14: Financial Forecast | H14: FY2023A | I14: FY2024A | J14: FY2025A | K14: FY2026F | L14: FY2027F | M14: FY2028F
B15: Revenue Growth | C15: - | D15: =Historical_IS!D4/Historical_IS!C4-1 -> 0.32729561 | E15: =Historical_IS!E4/Historical_IS!D4-1 -> 0.3957858 | G15: Revenue | H15: =Historical_IS!C4 -> 26749.821 | I15: =Historical_IS!D4 -> 35504.92 | J15: =Historical_IS!E4 -> 49557.263 | K15: =J15*(1+C20) -> 67472.214 | L15: =K15*(1+C20) -> 91863.419 | M15: =L15*(1+C20) -> 125072.04
B16: Profit Growth | C16: - | D16: =Historical_IS!D12/Historical_IS!C12-1 -> 0.17667385 | E16: =Historical_IS!E12/Historical_IS!D12-1 -> 0.27946826 | G16: Gross Profit | H16: =Historical_IS!C5 -> 16865.324 | I16: =Historical_IS!D5 -> 20380.554 | J16: =Historical_IS!E5 -> 27227.303 | K16: =J16*(1+C21) -> 43144.384 | L16: =K16*(1+C21) -> 68366.591 | M16: =L16*(1+C21) -> 108333.7
G17: Profit Before Tax | H17: =Historical_IS!C6 -> 15061.564 | I17: =Historical_IS!D6 -> 18899.78 | J17: =Historical_IS!E6 -> 25656.434 | K17: =J17*(1+C22) -> 39451.899 | L17: =K17*(1+C22) -> 60665.184 | M17: =L17*(1+C22) -> 93284.854
G18: Profit for the Year | H18: =Historical_IS!C12 -> 14829.15 | I18: =Historical_IS!D12 -> 17449.073 | J18: =Historical_IS!E12 -> 22325.535 | K18: =J18*(1+C23) -> 33461.512 | L18: =K18*(1+C23) -> 50152.114 | M18: =L18*(1+C23) -> 75167.988
B19: Assumption | C19: Forecast Assumptions
B20: Revenue | C20: 0.3615
B21: Gross Profit | C21: 0.5846
B22: Profit Before Tax | C22: 0.5377
B23: Profit for the Year | C23: 0.4988
